Workbook

Sheet Haircut
A1: Scenario 2 | B1: 0.25 | C1: std dev | E1: beta_UST | F1: 0.4330307 | G1: Duration | H1: 5
A2: Scenario 3 | B2: 0.5 | C2: std dev | E2: beta_rate | F2: 0.1251447
E3: beta_FX | F3: 0.0849102
A4: Scenario 2
A5: Dates | B5: quarter | C5: gdp | D5: reporate | E5: cpi | F5: forex | G5: property | H5: d_price | I5: d_property | J5: ust10y
A6: 46203 | B6: 265 | C6: =$B$1*_xlfn.STDEV.S(Macro!C$2:C$50) -> 0.57838184 | D6: =$B$1*_xlfn.STDEV.S(Macro!G$2:G$50) -> 0.23799291 | E6: =$B$1*_xlfn.STDEV.S(Macro!D$2:D$50) -> 0.41479567 | F6: =$B$1*_xlfn.STDEV.S(Macro!E$2:E$50) -> 330.49727 | G6: =$B$1*_xlfn.STDEV.S(Macro!F$2:F$50) -> 1.7439829 | H6: =$B$1*_xlfn.STDEV.S(Macro!I$2:I$50) -> 0.72721093 | I6: =$B$1*_xlfn.STDEV.S(Macro!J$2:J$50) -> 0.088132684 | J6: =$B$1*_xlfn.STDEV.S(Macro!K$2:K$50) -> 0.28680015
A7: 46295 | B7: 266 | C7: =$B$1*_xlfn.STDEV.S(Macro!C$2:C$50) -> 0.57838184 | D7: =$B$1*_xlfn.STDEV.S(Macro!G$2:G$50) -> 0.23799291 | E7: =$B$1*_xlfn.STDEV.S(Macro!D$2:D$50) -> 0.41479567 | F7: =$B$1*_xlfn.STDEV.S(Macro!E$2:E$50) -> 330.49727 | G7: =$B$1*_xlfn.STDEV.S(Macro!F$2:F$50) -> 1.7439829 | H7: =$B$1*_xlfn.STDEV.S(Macro!I$2:I$50) -> 0.72721093 | I7: =$B$1*_xlfn.STDEV.S(Macro!J$2:J$50) -> 0.088132684 | J7: =$B$1*_xlfn.STDEV.S(Macro!K$2:K$50) -> 0.28680015
A8: 46387 | B8: 267 | C8: =$B$1*_xlfn.STDEV.S(Macro!C$2:C$50) -> 0.57838184 | D8: =$B$1*_xlfn.STDEV.S(Macro!G$2:G$50) -> 0.23799291 | E8: =$B$1*_xlfn.STDEV.S(Macro!D$2:D$50) -> 0.41479567 | F8: =$B$1*_xlfn.STDEV.S(Macro!E$2:E$50) -> 330.49727 | G8: =$B$1*_xlfn.STDEV.S(Macro!F$2:F$50) -> 1.7439829 | H8: =$B$1*_xlfn.STDEV.S(Macro!I$2:I$50) -> 0.72721093 | I8: =$B$1*_xlfn.STDEV.S(Macro!J$2:J$50) -> 0.088132684 | J8: =$B$1*_xlfn.STDEV.S(Macro!K$2:K$50) -> 0.28680015
A9: 46477 | B9: 268 | C9: =$B$1*_xlfn.STDEV.S(Macro!C$2:C$50) -> 0.57838184 | D9: =$B$1*_xlfn.STDEV.S(Macro!G$2:G$50) -> 0.23799291 | E9: =$B$1*_xlfn.STDEV.S(Macro!D$2:D$50) -> 0.41479567 | F9: =$B$1*_xlfn.STDEV.S(Macro!E$2:E$50) -> 330.49727 | G9: =$B$1*_xlfn.STDEV.S(Macro!F$2:F$50) -> 1.7439829 | H9: =$B$1*_xlfn.STDEV.S(Macro!I$2:I$50) -> 0.72721093 | I9: =$B$1*_xlfn.STDEV.S(Macro!J$2:J$50) -> 0.088132684 | J9: =$B$1*_xlfn.STDEV.S(Macro!K$2:K$50) -> 0.28680015
A10: 46568 | B10: 269 | C10: =$B$1*_xlfn.STDEV.S(Macro!C$2:C$50) -> 0.57838184 | D10: =$B$1*_xlfn.STDEV.S(Macro!G$2:G$50) -> 0.23799291 | E10: =$B$1*_xlfn.STDEV.S(Macro!D$2:D$50) -> 0.41479567 | F10: =$B$1*_xlfn.STDEV.S(Macro!E$2:E$50) -> 330.49727 | G10: =$B$1*_xlfn.STDEV.S(Macro!F$2:F$50) -> 1.7439829 | H10: =$B$1*_xlfn.STDEV.S(Macro!I$2:I$50) -> 0.72721093 | I10: =$B$1*_xlfn.STDEV.S(Macro!J$2:J$50) -> 0.088132684 | J10: =$B$1*_xlfn.STDEV.S(Macro!K$2:K$50) -> 0.28680015
A11: 46660 | B11: 270 | C11: =$B$1*_xlfn.STDEV.S(Macro!C$2:C$50) -> 0.57838184 | D11: =$B$1*_xlfn.STDEV.S(Macro!G$2:G$50) -> 0.23799291 | E11: =$B$1*_xlfn.STDEV.S(Macro!D$2:D$50) -> 0.41479567 | F11: =$B$1*_xlfn.STDEV.S(Macro!E$2:E$50) -> 330.49727 | G11: =$B$1*_xlfn.STDEV.S(Macro!F$2:F$50) -> 1.7439829 | H11: =$B$1*_xlfn.STDEV.S(Macro!I$2:I$50) -> 0.72721093 | I11: =$B$1*_xlfn.STDEV.S(Macro!J$2:J$50) -> 0.088132684 | J11: =$B$1*_xlfn.STDEV.S(Macro!K$2:K$50) -> 0.28680015
A12: 46752 | B12: 271 | C12: =$B$1*_xlfn.STDEV.S(Macro!C$2:C$50) -> 0.57838184 | D12: =$B$1*_xlfn.STDEV.S(Macro!G$2:G$50) -> 0.23799291 | E12: =$B$1*_xlfn.STDEV.S(Macro!D$2:D$50) -> 0.41479567 | F12: =$B$1*_xlfn.STDEV.S(Macro!E$2:E$50) -> 330.49727 | G12: =$B$1*_xlfn.STDEV.S(Macro!F$2:F$50) -> 1.7439829 | H12: =$B$1*_xlfn.STDEV.S(Macro!I$2:I$50) -> 0.72721093 | I12: =$B$1*_xlfn.STDEV.S(Macro!J$2:J$50) -> 0.088132684 | J12: =$B$1*_xlfn.STDEV.S(Macro!K$2:K$50) -> 0.28680015
A14: Scenario 3
A15: Dates | B15: quarter | C15: gdp | D15: reporate | E15: cpi | F15: forex | G15: property | H15: d_price | I15: d_property | J15: ust10y
A16: 46203 | B16: 265 | C16: =$B$2*_xlfn.STDEV.S(Macro!C$2:C$50) -> 1.1567637 | D16: =$B$2*_xlfn.STDEV.S(Macro!G$2:G$50) -> 0.47598582 | E16: =$B$2*_xlfn.STDEV.S(Macro!D$2:D$50) -> 0.82959134 | F16: =$B$2*_xlfn.STDEV.S(Macro!E$2:E$50) -> 660.99453 | G16: =$B$2*_xlfn.STDEV.S(Macro!F$2:F$50) -> 3.4879657 | H16: =$B$2*_xlfn.STDEV.S(Macro!I$2:I$50) -> 1.4544219 | I16: =$B$2*_xlfn.STDEV.S(Macro!J$2:J$50) -> 0.17626537 | J16: =$B$2*_xlfn.STDEV.S(Macro!K$2:K$50) -> 0.5736003
A17: 46295 | B17: 266 | C17: =$B$2*_xlfn.STDEV.S(Macro!C$2:C$50) -> 1.1567637 | D17: =$B$2*_xlfn.STDEV.S(Macro!G$2:G$50) -> 0.47598582 | E17: =$B$2*_xlfn.STDEV.S(Macro!D$2:D$50) -> 0.82959134 | F17: =$B$2*_xlfn.STDEV.S(Macro!E$2:E$50) -> 660.99453 | G17: =$B$2*_xlfn.STDEV.S(Macro!F$2:F$50) -> 3.4879657 | H17: =$B$2*_xlfn.STDEV.S(Macro!I$2:I$50) -> 1.4544219 | I17: =$B$2*_xlfn.STDEV.S(Macro!J$2:J$50) -> 0.17626537 | J17: =$B$2*_xlfn.STDEV.S(Macro!K$2:K$50) -> 0.5736003
A18: 46387 | B18: 267 | C18: =$B$2*_xlfn.STDEV.S(Macro!C$2:C$50) -> 1.1567637 | D18: =$B$2*_xlfn.STDEV.S(Macro!G$2:G$50) -> 0.47598582 | E18: =$B$2*_xlfn.STDEV.S(Macro!D$2:D$50) -> 0.82959134 | F18: =$B$2*_xlfn.STDEV.S(Macro!E$2:E$50) -> 660.99453 | G18: =$B$2*_xlfn.STDEV.S(Macro!F$2:F$50) -> 3.4879657 | H18: =$B$2*_xlfn.STDEV.S(Macro!I$2:I$50) -> 1.4544219 | I18: =$B$2*_xlfn.STDEV.S(Macro!J$2:J$50) -> 0.17626537 | J18: =$B$2*_xlfn.STDEV.S(Macro!K$2:K$50) -> 0.5736003
A19: 46477 | B19: 268 | C19: =$B$2*_xlfn.STDEV.S(Macro!C$2:C$50) -> 1.1567637 | D19: =$B$2*_xlfn.STDEV.S(Macro!G$2:G$50) -> 0.47598582 | E19: =$B$2*_xlfn.STDEV.S(Macro!D$2:D$50) -> 0.82959134 | F19: =$B$2*_xlfn.STDEV.S(Macro!E$2:E$50) -> 660.99453 | G19: =$B$2*_xlfn.STDEV.S(Macro!F$2:F$50) -> 3.4879657 | H19: =$B$2*_xlfn.STDEV.S(Macro!I$2:I$50) -> 1.4544219 | I19: =$B$2*_xlfn.STDEV.S(Macro!J$2:J$50) -> 0.17626537 | J19: =$B$2*_xlfn.STDEV.S(Macro!K$2:K$50) -> 0.5736003
A20: 46568 | B20: 269 | C20: =$B$2*_xlfn.STDEV.S(Macro!C$2:C$50) -> 1.1567637 | D20: =$B$2*_xlfn.STDEV.S(Macro!G$2:G$50) -> 0.47598582 | E20: =$B$2*_xlfn.STDEV.S(Macro!D$2:D$50) -> 0.82959134 | F20: =$B$2*_xlfn.STDEV.S(Macro!E$2:E$50) -> 660.99453 | G20: =$B$2*_xlfn.STDEV.S(Macro!F$2:F$50) -> 3.4879657 | H20: =$B$2*_xlfn.STDEV.S(Macro!I$2:I$50) -> 1.4544219 | I20: =$B$2*_xlfn.STDEV.S(Macro!J$2:J$50) -> 0.17626537 | J20: =$B$2*_xlfn.STDEV.S(Macro!K$2:K$50) -> 0.5736003
A21: 46660 | B21: 270 | C21: =$B$2*_xlfn.STDEV.S(Macro!C$2:C$50) -> 1.1567637 | D21: =$B$2*_xlfn.STDEV.S(Macro!G$2:G$50) -> 0.47598582 | E21: =$B$2*_xlfn.STDEV.S(Macro!D$2:D$50) -> 0.82959134 | F21: =$B$2*_xlfn.STDEV.S(Macro!E$2:E$50) -> 660.99453 | G21: =$B$2*_xlfn.STDEV.S(Macro!F$2:F$50) -> 3.4879657 | H21: =$B$2*_xlfn.STDEV.S(Macro!I$2:I$50) -> 1.4544219 | I21: =$B$2*_xlfn.STDEV.S(Macro!J$2:J$50) -> 0.17626537 | J21: =$B$2*_xlfn.STDEV.S(Macro!K$2:K$50) -> 0.5736003
A22: 46752 | B22: 271 | C22: =$B$2*_xlfn.STDEV.S(Macro!C$2:C$50) -> 1.1567637 | D22: =$B$2*_xlfn.STDEV.S(Macro!G$2:G$50) -> 0.47598582 | E22: =$B$2*_xlfn.STDEV.S(Macro!D$2:D$50) -> 0.82959134 | F22: =$B$2*_xlfn.STDEV.S(Macro!E$2:E$50) -> 660.99453 | G22: =$B$2*_xlfn.STDEV.S(Macro!F$2:F$50) -> 3.4879657 | H22: =$B$2*_xlfn.STDEV.S(Macro!I$2:I$50) -> 1.4544219 | I22: =$B$2*_xlfn.STDEV.S(Macro!J$2:J$50) -> 0.17626537 | J22: =$B$2*_xlfn.STDEV.S(Macro!K$2:K$50) -> 0.5736003

Sheet Macro
A1: Dates | B1: quarter | C1: gdp | D1: cpi | E1: forex | F1: property | G1: reporate | H1: d_repo | I1: d_price | J1: d_property | K1: ust10y | L1: sbn10y
A2: 41820 | B2: 217 | C2: 4.94 | D2: 6.7 | E2: 11855 | F2: 85.750547 | G2: 6.25 | K2: 2.5304 | L2: 8.213
A3: 41912 | B3: =B2+1 -> 218 | C3: 4.93 | D3: 4.53 | E3: 12182.5 | F3: 87.002505 | G3: 6.25 | H3: =G3-G2 -> 0 | I3: =-Haircut!$H$1*(L3-L2) -> -1.54 | J3: =F3-F2 -> 1.251958 | K3: 2.4888 | L3: 8.521
A4: 42004 | B4: =B3+1 -> 219 | C4: 5.05 | D4: 8.36 | E4: 12385 | F4: 88.342343 | G4: 6.5 | H4: =G4-G3 -> 0.25 | I4: =-Haircut!$H$1*(L4-L3) -> 3.625 | J4: =F4-F3 -> 1.3398386 | K4: 2.1712 | L4: 7.796
A5: 42094 | B5: =B4+1 -> 220 | C5: 4.83 | D5: 6.38 | E5: 13075 | F5: 89.614473 | G5: 6.25 | H5: =G5-G4 -> -0.25 | I5: =-Haircut!$H$1*(L5-L4) -> 1.195 | J5: =F5-F4 -> 1.2721297 | K5: 1.9231 | L5: 7.557
A6: 42185 | B6: =B5+1 -> 221 | C6: 4.74 | D6: 7.26 | E6: 13332.8 | F6: 90.851153 | G6: 6.25 | H6: =G6-G5 -> 0 | I6: =-Haircut!$H$1*(L6-L5) -> -4.13 | J6: =F6-F5 -> 1.2366797 | K6: 2.3531 | L6: 8.383
A7: 42277 | B7: =B6+1 -> 222 | C7: 4.78 | D7: 6.83 | E7: 14651.3 | F7: 91.750579 | G7: 6.25 | H7: =G7-G6 -> 0 | I7: =-Haircut!$H$1*(L7-L6) -> -6.54 | J7: =F7-F6 -> 0.89942641 | K7: 2.0368 | L7: 9.691
A8: 42369 | B8: =B7+1 -> 223 | C8: 5.15 | D8: 3.35 | E8: 13787.5 | F8: 92.420358 | G8: 6.25 | H8: =G8-G7 -> 0 | I8: =-Haircut!$H$1*(L8-L7) -> 3.49 | J8: =F8-F7 -> 0.66977923 | K8: 2.2694 | L8: 8.993
A9: 42460 | B9: =B8+1 -> 224 | C9: 4.94 | D9: 4.45 | E9: 13260 | F9: 93.33532 | G9: 5.5 | H9: =G9-G8 -> -0.75 | I9: =-Haircut!$H$1*(L9-L8) -> 6.625 | J9: =F9-F8 -> 0.91496155 | K9: 1.7687 | L9: 7.668
A10: 42551 | B10: =B9+1 -> 225 | C10: 5.21 | D10: 3.45 | E10: 13220 | F10: 93.932666 | G10: 5.25 | H10: =G10-G9 -> -0.25 | I10: =-Haircut!$H$1*(L10-L9) -> 1.075 | J10: =F10-F9 -> 0.59734605 | K10: 1.4697 | L10: 7.453
A11: 42643 | B11: =B10+1 -> 226 | C11: 5.03 | D11: 3.07 | E11: 13051 | F11: 94.270824 | G11: 4.75 | H11: =G11-G10 -> -0.5 | I11: =-Haircut!$H$1*(L11-L10) -> 1.96 | J11: =F11-F10 -> 0.3381576 | K11: 1.5944 | L11: 7.061
A12: 42735 | B12: =B11+1 -> 227 | C12: 4.94 | D12: 3.02 | E12: 13472.5 | F12: 94.619626 | G12: 4.75 | H12: =G12-G11 -> 0 | I12: =-Haircut!$H$1*(L12-L11) -> -4.56 | J12: =F12-F11 -> 0.34880205 | K12: 2.4443 | L12: 7.973
A13: 42825 | B13: =B12+1 -> 228 | C13: 5.01 | D13: 3.61 | E13: 13325.5 | F13: 95.783447 | G13: 4.75 | H13: =G13-G12 -> 0 | I13: =-Haircut!$H$1*(L13-L12) -> 4.65 | J13: =F13-F12 -> 1.1638214 | K13: 2.3874 | L13: 7.043
A14: 42916 | B14: =B13+1 -> 229 | C14: 5.01 | D14: 4.37 | E14: 13327.5 | F14: 96.913692 | G14: 4.75 | H14: =G14-G13 -> 0 | I14: =-Haircut!$H$1*(L14-L13) -> 1.07 | J14: =F14-F13 -> 1.1302447 | K14: 2.3037 | L14: 6.829
... A32: 44561 | B32: =B31+1 -> 247 | C32: 5.03 | D32: 1.87 | E32: 14252.5 | F32: 104.21267 | G32: 3.5 | H32: =G32-G31 -> 0 | I32: =-Haircut!$H$1*(L32-L31) -> -0.605 | J32: =F32-F31 -> 0.42250001 | K32: 1.5101 | L32: 6.382
A33: 44651 | B33: =B32+1 -> 248 | C33: 5.02 | D33: 2.64 | E33: 14369 | F33: 104.87 | G33: 3.5 | H33: =G33-G32 -> 0 | I33: =-Haircut!$H$1*(L33-L32) -> -1.78 | J33: 0.65733134 | K33: 2.338 | L33: 6.738
A34: 44742 | B34: =B33+1 -> 249 | C34: 5.46 | D34: 4.35 | E34: 14897.5 | F34: 105.23 | G34: 3.5 | H34: =G34-G33 -> 0 | I34: =-Haircut!$H$1*(L34-L33) -> -2.41 | J34: 0.36 | K34: 3.0129 | L34: 7.22
A35: 44834 | B35: =B34+1 -> 250 | C35: 5.73 | D35: 5.95 | E35: 15227.5 | F35: 105.8 | G35: 4.25 | H35: =G35-G34 -> 0.75 | I35: =-Haircut!$H$1*(L35-L34) -> -0.765 | J35: 0.57 | K35: 3.8286 | L35: 7.373
A36: 44926 | B36: =B35+1 -> 251 | C36: 5.01 | D36: 5.51 | E36: 15567.5 | F36: 106.3 | G36: 5.5 | H36: =G36-G35 -> 1.25 | I36: =-Haircut!$H$1*(L36-L35) -> 2.165 | J36: 0.5 | K36: 3.8748 | L36: 6.94
A37: 45016 | B37: =B36+1 -> 252 | C37: 5.03 | D37: 4.97 | E37: 14994.5 | F37: 106.75 | G37: 5.75 | H37: =G37-G36 -> 0.25 | I37: =-Haircut!$H$1*(L37-L36) -> 0.735 | J37: 0.45 | K37: 3.4676 | L37: 6.793
A38: 45107 | B38: 253 | C38: 5.17 | D38: 3.52 | E38: 14869.857 | F38: 107.26 | G38: 5.75 | H38: =G38-G37 -> 0 | I38: =-Haircut!$H$1*(L38-L37) -> 2.66 | J38: 0.51 | K38: 3.8367 | L38: 6.261
A39: 45199 | B39: 254 | C39: 4.94 | D39: 2.28 | E39: 15213.029 | F39: 107.87 | G39: 6 | H39: =G39-G38 -> 0.25 | I39: =-Haircut!$H$1*(L39-L38) -> -3.265 | J39: 0.61 | K39: 4.5711 | L39: 6.914
A40: 45291 | B40: 255 | C40: 5.04 | D40: 2.81 | E40: 15629.27 | F40: 108.15 | G40: 6 | H40: =G40-G39 -> 0 | I40: =-Haircut!$H$1*(L40-L39) -> 2.17 | J40: 0.28 | K40: 3.8791 | L40: 6.48
A41: 45382 | B41: 256 | C41: 5.11 | D41: 3.05 | E41: 15656.22 | F41: 108.76 | G41: 6 | H41: =G41-G40 -> 0 | I41: =-Haircut!$H$1*(L41-L40) -> -1.065 | J41: 0.61 | K41: 4.2003 | L41: 6.693
A42: 45473 | B42: 257 | C42: 5.05 | D42: 2.51 | E42: 16394 | F42: 109.15 | G42: 6.25 | H42: =G42-G41 -> 0.25 | I42: =-Haircut!$H$1*(L42-L41) -> -1.9 | J42: 0.39 | K42: 4.3961 | L42: 7.073
A43: 45565 | B43: 258 | C43: 4.95 | D43: 1.84 | E43: 15144 | F43: 109.44 | G43: 6 | H43: -0.25 | I43: =-Haircut!$H$1*(L43-L42) -> 3.1 | J43: 0.29 | K43: 3.7809 | L43: 6.453
A44: 45657 | B44: 259 | C44: 5.02 | D44: 1.57 | E44: 16157 | F44: 109.65 | G44: 6 | H44: 0 | I44: =-Haircut!$H$1*(L44-L43) -> -2.72 | J44: 0.21 | K44: 4.569 | L44: 6.997
A45: 45747 | B45: 260 | C45: 4.87 | D45: 1.03 | E45: 16566 | F45: 109.93 | G45: 5.75 | H45: -0.25 | I45: =-Haircut!$H$1*(L45-L44) -> -0.035 | J45: 0.28 | K45: 4.2053 | L45: 7.004
A46: 45838 | B46: 261 | C46: 5.12 | D46: 1.87 | E46: 16231 | F46: 110.13 | G46: 5.5 | H46: -0.25 | I46: =-Haircut!$H$1*(L46-L45) -> 1.88 | J46: 0.2 | K46: 4.228 | L46: 6.628
A47: 45930 | B47: 262 | C47: 5.04 | D47: 2.65 | E47: 16692 | F47: 110.36 | G47: 4.75 | H47: -0.75 | I47: =-Haircut!$H$1*(L47-L46) -> 1.305 | J47: 0.23 | K47: 4.1503 | L47: 6.367
A48: 46022 | B48: 263 | C48: 5.39 | D48: 2.92 | E48: 16782 | F48: 110.56 | G48: 4.75 | H48: 0 | I48: =-Haircut!$H$1*(L48-L47) -> 1.485 | J48: 0.2 | K48: 4.167 | L48: 6.07
A49: 46112 | B49: 264 | C49: 5.61 | D49: 3.48 | E49: 16999 | F49: 110.6 | G49: 4.75 | H49: 0 | I49: =-Haircut!$H$1*(L49-L48) -> -3.925 | J49: 0.04 | K49: 4.3166 | L49: 6.855
A50: 46203 | B50: 265 | C50: 5.29 | D50: 3.34 | E50: 17899 | F50: 110.89 | G50: 5.75 | H50: 1 | I50: =-Haircut!$H$1*(L50-L49) -> -1.515 | J50: 0.29 | K50: 4.4652 | L50: 7.158

Sheet Scenario 1
A1: Dates | B1: gdp | C1: reporate | D1: cpi | E1: forex | F1: d_property | G1: d_price | H1: d_repo | I1: quarter | J1: ust10y | K1: sbn10y
A2: 46295 | B2: 5.1 | C2: 5.75 | D2: 3.28 | E2: 17877 | F2: 0.25 | G2: =-Haircut!$H$1*(K2-Macro!L50) -> 0.315 | H2: =C2-Macro!G50 -> 0 | I2: 266 | J2: 4.9613 | K2: 7.095
A3: 46387 | B3: 5.1 | C3: 5.75 | D3: 3.2 | E3: 17800 | F3: 0.25 | G3: =-Haircut!$H$1*(K3-K2) -> 0.183258 | H3: =C3-C2 -> 0 | I3: 267 | J3: =J2 -> 4.9613 | K3: =K2+Haircut!$F$1*(J3-J2)+Haircut!$F$2*(C3-C2)+Haircut!$F$3*100*LN(E3/E2) -> 7.0583484
A4: 46477 | B4: 5.1 | C4: 5.5 | D4: 3 | E4: 17600 | F4: 0.25 | G4: =-Haircut!$H$1*(K4-K3) -> 0.63615462 | H4: =C4-C3 -> -0.25 | I4: 268 | J4: =J3 -> 4.9613 | K4: =K3+Haircut!$F$1*(J4-J3)+Haircut!$F$2*(C4-C3)+Haircut!$F$3*100*LN(E4/E3) -> 6.9311175
A5: 46568 | B5: 5.2 | C5: 5.25 | D5: 3 | E5: 17500 | F5: 0.25 | G5: =-Haircut!$H$1*(K5-K4) -> 0.39834093 | H5: =C5-C4 -> -0.25 | I5: 269 | J5: =J4 -> 4.9613 | K5: =K4+Haircut!$F$1*(J5-J4)+Haircut!$F$2*(C5-C4)+Haircut!$F$3*100*LN(E5/E4) -> 6.8514493
A6: 46660 | B6: 5.2 | C6: 5.25 | D6: 2.9 | E6: 17400 | F6: 0.25 | G6: =-Haircut!$H$1*(K6-K5) -> 0.24329637 | H6: =C6-C5 -> 0 | I6: 270 | J6: =J5 -> 4.9613 | K6: =K5+Haircut!$F$1*(J6-J5)+Haircut!$F$2*(C6-C5)+Haircut!$F$3*100*LN(E6/E5) -> 6.80279
A7: 46752 | B7: 5.2 | C7: 5 | D7: 2.8 | E7: 17300 | F7: 0.25 | G7: =-Haircut!$H$1*(K7-K6) -> 0.40112954 | H7: =C7-C6 -> -0.25 | I7: 271 | J7: =J6 -> 4.9613 | K7: =K6+Haircut!$F$1*(J7-J6)+Haircut!$F$2*(C7-C6)+Haircut!$F$3*100*LN(E7/E6) -> 6.7225641

Sheet Scenario 2
A1: Dates | B1: gdp | C1: reporate | D1: cpi | E1: forex | F1: d_property | G1: d_price | H1: quarter | I1: ust10y | J1: sbn10y
A2: 46295 | B2: =Macro!C50-Haircut!C6 -> 4.7116182 | C2: ='Scenario 1'!C2 -> 5.75 | D2: =Macro!D50+Haircut!E7 -> 3.7547957 | E2: ='Scenario 1'!E2+Haircut!F6 -> 18207.497 | F2: =Macro!J50-Haircut!I7 -> 0.20186732 | G2: =-Haircut!$H$1*(J2-Macro!L50) -> -1.0836791 | H2: 266 | I2: ='Scenario 1'!J2+Haircut!J7 -> 5.2481001 | J2: ='Scenario 1'!K2+Haircut!$F$1*(I2-'Scenario 1'!J2)+Haircut!$F$2*(C2-'Scenario 1'!C2)+Haircut!$F$3*100*LN(E2/'Scenario 1'!E2) -> 7.3747358
A3: 46387 | B3: =B2-Haircut!C6 -> 4.1332363 | C3: =C2-Haircut!D7 -> 5.5120071 | D3: =D2+Haircut!E7 -> 4.1695913 | E3: =E2+Haircut!F7 -> 18537.995 | F3: 0.36 | G3: =-Haircut!$H$1*(J3-J2) -> -1.2357707 | H3: 267 | I3: =I2+('Scenario 1'!J3-'Scenario 1'!J2)+Haircut!J8 -> 5.5349003 | J3: =J2+Haircut!$F$1*(I3-I2)+Haircut!$F$2*(C3-C2)+Haircut!$F$3*100*LN(E3/E2) -> 7.62189
A4: 46477 | B4: =B3-Haircut!C7 -> 3.5548545 | C4: =C3-Haircut!D8 -> 5.2740142 | D4: =D3+Haircut!E8 -> 4.584387 | E4: =E3+Haircut!F8 -> 18868.492 | F4: 0 | G4: =-Haircut!$H$1*(J4-J3) -> -1.2222746 | H4: 268 | I4: =I3+('Scenario 1'!J4-'Scenario 1'!J3)+Haircut!J9 -> 5.8217004 | J4: =J3+Haircut!$F$1*(I4-I3)+Haircut!$F$2*(C4-C3)+Haircut!$F$3*100*LN(E4/E3) -> 7.8663449
A5: 46568 | B5: =B4-Haircut!C8 -> 2.9764727 | C5: =C4-Haircut!D9 -> 5.0360213 | D5: =D4+Haircut!E9 -> 4.9991827 | E5: =E4+Haircut!F9 -> 19198.989 | F5: 0.10715616 | G5: =-Haircut!$H$1*(J5-J4) -> -1.2092472 | H5: 269 | I5: =I4+('Scenario 1'!J5-'Scenario 1'!J4)+Haircut!J10 -> 6.1085006 | J5: =J4+Haircut!$F$1*(I5-I4)+Haircut!$F$2*(C5-C4)+Haircut!$F$3*100*LN(E5/E4) -> 8.1081943
A6: 46660 | B6: ='Scenario 2'!B5-Haircut!C9 -> 2.3980908 | C6: =C5-Haircut!D10 -> 4.7980284 | D6: ='Scenario 2'!D5+Haircut!E10 -> 5.4139783 | E6: ='Scenario 2'!E5+Haircut!F10 -> 19529.486 | F6: -0.22045845 | G6: =-Haircut!$H$1*(J6-J5) -> -1.1966645 | H6: 270 | I6: =I5+('Scenario 1'!J6-'Scenario 1'!J5)+Haircut!J11 -> 6.3953007 | J6: =J5+Haircut!$F$1*(I6-I5)+Haircut!$F$2*(C6-C5)+Haircut!$F$3*100*LN(E6/E5) -> 8.3475272
A7: 46752 | B7: =B6-Haircut!C10 -> 1.819709 | C7: =C6-Haircut!D11 -> 4.5600355 | D7: =D6+Haircut!E11 -> 5.828774 | E7: =E6+Haircut!F11 -> 19859.984 | F7: -0.54807306 | G7: =-Haircut!$H$1*(J7-J6) -> -1.1845042 | H7: 271 | I7: =I6+('Scenario 1'!J7-'Scenario 1'!J6)+Haircut!J12 -> 6.6821009 | J7: =J6+Haircut!$F$1*(I7-I6)+Haircut!$F$2*(C7-C6)+Haircut!$F$3*100*LN(E7/E6) -> 8.5844281

Sheet Scenario 3
A1: Dates | B1: gdp | C1: reporate | D1: cpi | E1: forex | F1: d_property | G1: d_price | H1: quarter | I1: ust10y | J1: sbn10y
A2: 46295 | B2: =Macro!C50-Haircut!C16 -> 4.1332363 | C2: ='Scenario 1'!C2 -> 5.75 | D2: =Macro!D50+Haircut!E17 -> 4.1695913 | E2: ='Scenario 1'!E2+Haircut!F16 -> 18537.995 | F2: =Macro!J50-Haircut!I17 -> 0.11373463 | G2: =-Haircut!$H$1*(J2-Macro!L50) -> -2.4683676 | H2: 266 | I2: ='Scenario 1'!J2+Haircut!J17 -> 5.5349003 | J2: ='Scenario 1'!K2+Haircut!$F$1*(I2-'Scenario 1'!J2)+Haircut!$F$2*(C2-'Scenario 1'!C2)+Haircut!$F$3*100*LN(E2/'Scenario 1'!E2) -> 7.6516735
A3: 46387 | B3: =B2-Haircut!C18 -> 2.9764727 | C3: =C2+Haircut!D8 -> 5.9879929 | D3: =D2+Haircut!E17 -> 4.9991827 | E3: =E2+Haircut!F17 -> 19198.989 | F3: -1.39 | G3: =-Haircut!$H$1*(J3-J2) -> -2.8782751 | H3: 267 | I3: =I2+('Scenario 1'!J3-'Scenario 1'!J2)+Haircut!J18 -> 6.1085006 | J3: =J2+Haircut!$F$1*(I3-I2)+Haircut!$F$2*(C3-C2)+Haircut!$F$3*100*LN(E3/E2) -> 8.2273285
A4: 46477 | B4: =B3-Haircut!C19 -> 1.819709 | C4: =C3+Haircut!D9 -> 6.2259858 | D4: =D3+Haircut!E18 -> 5.828774 | E4: =E3+Haircut!F18 -> 19859.984 | F4: -2.65 | G4: =-Haircut!$H$1*(J4-J3) -> -2.827922 | H4: 268 | I4: =I3+('Scenario 1'!J4-'Scenario 1'!J3)+Haircut!J19 -> 6.6821009 | J4: =J3+Haircut!$F$1*(I4-I3)+Haircut!$F$2*(C4-C3)+Haircut!$F$3*100*LN(E4/E3) -> 8.7929129
A5: 46568 | B5: =B4-Haircut!C20 -> 0.66294532 | C5: =C4+Haircut!D10 -> 6.4639787 | D5: =D4+Haircut!E19 -> 6.6583654 | E5: =E4+Haircut!F19 -> 20520.978 | F5: -2.57 | G5: =-Haircut!$H$1*(J5-J4) -> -2.7808667 | H5: 269 | I5: =I4+('Scenario 1'!J5-'Scenario 1'!J4)+Haircut!J20 -> 7.2557012 | J5: =J4+Haircut!$F$1*(I5-I4)+Haircut!$F$2*(C5-C4)+Haircut!$F$3*100*LN(E5/E4) -> 9.3490863
A6: 46660 | B6: ='Scenario 3'!B5-Haircut!C21 -> -0.49381835 | C6: ='Scenario 3'!C5+Haircut!D11 -> 6.7019716 | D6: ='Scenario 3'!D5+Haircut!E20 -> 7.4879567 | E6: ='Scenario 3'!E5+Haircut!F20 -> 21181.973 | F6: -1.12 | G6: =-Haircut!$H$1*(J6-J5) -> -2.7367955 | H6: 270 | I6: =I5+('Scenario 1'!J6-'Scenario 1'!J5)+Haircut!J21 -> 7.8293015 | J6: =J5+Haircut!$F$1*(I6-I5)+Haircut!$F$2*(C6-C5)+Haircut!$F$3*100*LN(E6/E5) -> 9.8964453
A7: 46752 | B7: =B6-Haircut!C22 -> -1.650582 | C7: =C6+Haircut!D12 -> 6.9399645 | D7: =D6+Haircut!E21 -> 8.317548 | E7: =E6+Haircut!F21 -> 21842.967 | F7: -0.62 | G7: =-Haircut!$H$1*(J7-J6) -> -2.6954332 | H7: 271 | I7: =I6+('Scenario 1'!J7-'Scenario 1'!J6)+Haircut!J22 -> 8.4029018 | J7: =J6+Haircut!$F$1*(I7-I6)+Haircut!$F$2*(C7-C6)+Haircut!$F$3*100*LN(E7/E6) -> 10.435532

Sheet Presentation
A1: GDP | B1: Baseline | C1: Adverse 1 | D1: Adverse 2
A2: 2026Q2 | B2: =Macro!C50 -> 5.29 | C2: =Macro!C50 -> 5.29 | D2: =Macro!C50 -> 5.29
A3: 2026Q3 | B3: ='Scenario 1'!B2 -> 5.1 | C3: ='Scenario 2'!B2 -> 4.7116182 | D3: ='Scenario 3'!B2 -> 4.1332363
A4: 2026Q4 | B4: ='Scenario 1'!B3 -> 5.1 | C4: ='Scenario 2'!B3 -> 4.1332363 | D4: ='Scenario 3'!B3 -> 2.9764727
A5: 2027Q1 | B5: ='Scenario 1'!B4 -> 5.1 | C5: ='Scenario 2'!B4 -> 3.5548545 | D5: ='Scenario 3'!B4 -> 1.819709
A6: 2027Q2 | B6: ='Scenario 1'!B5 -> 5.2 | C6: ='Scenario 2'!B5 -> 2.9764727 | D6: ='Scenario 3'!B5 -> 0.66294532
A8: 7DRR | B8: Baseline | C8: Adverse 1 | D8: Adverse 2
A9: 2026Q3 | B9: ='Scenario 1'!C2 -> 5.75 | C9: ='Scenario 2'!C2 -> 5.75 | D9: ='Scenario 3'!C2 -> 5.75
A10: 2026Q4 | B10: ='Scenario 1'!C3 -> 5.75 | C10: ='Scenario 2'!C3 -> 5.5120071 | D10: ='Scenario 3'!C3 -> 5.9879929
A11: 2027Q1 | B11: ='Scenario 1'!C4 -> 5.5 | C11: ='Scenario 2'!C4 -> 5.2740142 | D11: ='Scenario 3'!C4 -> 6.2259858
A12: 2027Q2 | B12: ='Scenario 1'!C5 -> 5.25 | C12: ='Scenario 2'!C5 -> 5.0360213 | D12: ='Scenario 3'!C5 -> 6.4639787
A15: Housing | B15: Baseline | C15: Adverse 1 | D15: Adverse 2
A16: 2026Q2 | B16: =Macro!J50 -> 0.29 | C16: 0.38586168 | D16: 0.38586168
A17: 2026Q3 | B17: ='Scenario 1'!F2 -> 0.25 | C17: ='Scenario 2'!F2 -> 0.20186732 | D17: ='Scenario 3'!F2 -> 0.11373463
A18: 2026Q4 | B18: ='Scenario 1'!F3 -> 0.25 | C18: ='Scenario 2'!F3 -> 0.36 | D18: ='Scenario 3'!F3 -> -1.39
A19: 2027Q1 | B19: ='Scenario 1'!F4 -> 0.25 | C19: ='Scenario 2'!F4 -> 0 | D19: ='Scenario 3'!F4 -> -2.65
A20: 2027Q2 | B20: ='Scenario 1'!F5 -> 0.25 | C20: ='Scenario 2'!F5 -> 0.10715616 | D20: ='Scenario 3'!F5 -> -2.57
A22: Bond Price | B22: Baseline | C22: Adverse 1 | D22: Adverse 2
A23: 2026Q3 | B23: ='Scenario 1'!G2 -> 0.315 | C23: ='Scenario 2'!G2 -> -1.0836791 | D23: ='Scenario 3'!G2 -> -2.4683676
A24: 2026Q4 | B24: ='Scenario 1'!G3 -> 0.183258 | C24: ='Scenario 2'!G3 -> -1.2357707 | D24: ='Scenario 3'!G3 -> -2.8782751
A25: 2027Q1 | B25: ='Scenario 1'!G4 -> 0.63615462 | C25: ='Scenario 2'!G4 -> -1.2222746 | D25: ='Scenario 3'!G4 -> -2.827922
A26: 2027Q2 | B26: ='Scenario 1'!G5 -> 0.39834093 | C26: ='Scenario 2'!G5 -> -1.2092472 | D26: ='Scenario 3'!G5 -> -2.7808667

Sheet Parameters
A1: parameter | B1: value | C1: description | D1: source / date
A2: srbi_bank | B2: 607.62 | C2: SRBI owned by banks (Rp trillion) - INPUT | D2: BI, Ownership of SRBI, 30 Sep 2026 (row Bank)
A3: srbi_repo | B3: 78.69 | C3: SRBI under repo to BI (Rp trillion) - INPUT | D3: BI, Ownership of SRBI, 30 Sep 2026 (row Others*)
A4: sbn_bank | B4: 1209.49 | C4: SBN held by banks incl. repo with BI (Rp trillion) - INPUT | D4: DJPPR, Kepemilikan SBN yang dapat diperdagangkan, 1 Oct 2026 (row BANK*)
A5: w_srbi | B5: =(B2+B3)/(B2+B3+B4) -> 0.36201604 | C5: SRBI share of bank securities; held to maturity, no MTM loss | D5: formula
A6: D_sbn | B6: 5 | C6: Modified duration of the SBN book (price change = -D x change in SBN 10Y yield) | D6: assumption
A7: payout | B7: 0.5 | C7: Dividend payout on positive profit | D7: assumption
A8: k_stress | B8: 0.05 | C8: Stress provision add-on per pp GDP gap vs baseline, x NPL stock, per quarter | D8: calibrated: Adverse 2 credit loss ~ 2021 peak (11.5% of capital)
A9: tax_rate | B9: 0.22 | C9: Corporate income tax rate | D9: assumption
